sycutestlib/MyModule.py
sycutestlib/__init__.py
SycuTestLib-0.1.dist-info/METADATA
SycuTestLib-0.1.dist-info/WHEEL
SycuTestLib-0.1.dist-info/top_level.txt
SycuTestLib-0.1.dist-info/RECORD
