Metadata-Version: 2.1
Name: SycuTestLib
Version: 0.1
Summary: This is a Test Lib
Home-page: https://github.com/tanxinyue/multable
Author: LiChunYu
Author-email: 28898830@qq.com
License: SYCU
Keywords: Test
Platform: UNKNOWN
Classifier: Development Status :: 3 - Alpha
Classifier: Intended Audience :: Developers
Classifier: Topic :: Software Development :: Build Tools
Classifier: License :: OSI Approved :: MIT License
Classifier: Programming Language :: Python :: 3
Classifier: Programming Language :: Python :: 3.3
Classifier: Programming Language :: Python :: 3.4
Classifier: Programming Language :: Python :: 3.5
